zeroscale/__docker__.py
zeroscale/__init__.py
zeroscale/__main__.py
zeroscale/base_server.py
zeroscale/docker.py
zeroscale/parser.py
zeroscale/proxy.py
zeroscale/status.py
zeroscale/zeroscale.py
zeroscale/plugins/__init__.py
zeroscale/plugins/generic.py
zeroscale/plugins/minecraft.py
zeroscale/plugins/terraria.py
zeroscale-0.5.2.dist-info/LICENSE
zeroscale-0.5.2.dist-info/METADATA
zeroscale-0.5.2.dist-info/WHEEL
zeroscale-0.5.2.dist-info/entry_points.txt
zeroscale-0.5.2.dist-info/top_level.txt
zeroscale-0.5.2.dist-info/RECORD
