Metadata-Version: 2.1
Name: zeroscale
Version: 0.5.2
Summary: Scale-to-zero any server
Home-page: https://github.com/Rycieos/zeroscale
Author: Mark Vander Stel
Author-email: mvndrstl@gmail.com
License: UNKNOWN
Platform: UNKNOWN
Classifier: Development Status :: 4 - Beta
Classifier: License :: OSI Approved :: GNU General Public License v3 (GPLv3)
Classifier: Operating System :: OS Independent
Classifier: Programming Language :: Python :: 3
Classifier: Programming Language :: Python :: 3.5
Classifier: Programming Language :: Python :: 3.6
Classifier: Programming Language :: Python :: 3.7
Classifier: Programming Language :: Python :: 3.8
Classifier: Programming Language :: Python :: 3.9
Requires-Python: >=3.5
Provides-Extra: docker
Requires-Dist: docker (<5.0,>=4.0) ; extra == 'docker'
Provides-Extra: test
Requires-Dist: coveralls (<3.0,>=2.0) ; extra == 'test'
Requires-Dist: pytest (<6.0,>=5.4) ; extra == 'test'
Requires-Dist: pytest-asyncio (<0.13.0,>=0.12.0) ; extra == 'test'
Requires-Dist: pytest-cov (<3.0,>=2.6.1) ; extra == 'test'
